[
    {
        "type": "user",
        "id": 34729910,
        "permalink": "https://soundcloud.com/joy-orbison",
        "name": "Joy Orbison",
        "likeCount": 13,
        "city": "London",
        "countryCode": "GB",
        "gender": "M",
        "genres": {
            "ra ": 1,
            "ttt": 1,
            "zoo talking": 1,
            "joy orbison": 1,
            "electronic": 2,
            "techno": 1
        }
    },
    {
        "type": "user",
        "id": 8337344,
        "permalink": "https://soundcloud.com/harrison",
        "name": "Harrison",
        "likeCount": 51,
        "city": "London",
        "countryCode": "GB",
        "gender": "M",
        "genres": {
            "electronic": 2,
            "acapella": 1,
            "deep house": 3,
            "dance": 4,
            "dance & edm": 9,
            "vinai": 1,
            "classical": 1,
            "trap": 1,
            "progressive house": 2,
            "harrison": 4,
            "harrison!": 2,
            "house": 1,
            "electro house": 2,
            "house ": 1,
            "laidback luke ": 1,
            "hardstyle": 1,
            "neonfuture": 1,
            "mayday ": 1,
            "pop": 1
        }
    },
    {
        "type": "user",
        "id": 252392457,
        "permalink": "https://soundcloud.com/djreevesuk8701",
        "name": "Dj David Reeves IG @djreeves_uk8701",
        "likeCount": 50,
        "city": "london",
        "countryCode": "GB",
        "gender": "M",
        "genres": {
            "r&b": 1,
            "newafrobeatsamapiano": 1,
            "afrobeats": 2,
            "afrobeats vs amapiano": 1,
            "rnb slow vibes": 1,
            "afrobeats / amapiano": 1,
            "amapiano": 1,
            "fem remix afrobeats": 1,
            "entertainment": 1,
            "hip-hop & rap": 2,
            "dancehall": 4,
            "rnb": 1,
            "r&b & soul": 4,
            "deep house": 1,
            "world": 2,
            "dj": 1,
            "afrobeats madness vol 3": 1,
            "afro.beast mix": 1,
            "afro.beast mix 2019": 1,
            "old skool": 1,
            "kisstory": 1,
            "nigerian afrobeats": 1
        }
    },
    {
        "type": "user",
        "id": 10791419,
        "permalink": "https://soundcloud.com/david_taro",
        "name": "david taro",
        "likeCount": 501,
        "city": "London",
        "countryCode": "GB",
        "gender": "M",
        "genres": {
            "folk & singer-songwriter": 21,
            "brixton road": 2,
            "r&b/pop": 1,
            "christmas rock": 1,
            "hard rock": 1,
            "r&b & soul": 3,
            "indie": 3,
            "oriental": 1,
            "song": 1,
            "reggae": 1,
            "rock": 2,
            "jazz & blues": 1,
            "pop": 2,
            "electronic": 3
        }
    },
    {
        "type": "user",
        "id": 1080469,
        "permalink": "https://soundcloud.com/david-toop",
        "name": "David Toop",
        "likeCount": 2,
        "city": "London",
        "countryCode": "GB",
        "gender": "M",
        "genres": {
            "new music podcast": 1,
            "dance": 1
        }
    },
    {
        "type": "user",
        "id": 922,
        "permalink": "https://soundcloud.com/paulmac",
        "name": "Paul Mac",
        "likeCount": 301,
        "city": "London",
        "countryCode": null,
        "gender": "M",
        "genres": {
            "techno": 12,
            "hardgroove rollers": 1,
            "drum & bass": 4,
            "everything": 1,
            "magnonic signals": 1,
            "dub techno #deep techno": 1,
            "jungle": 1,
            "dance & edm": 1,
            "subwax excursions": 1,
            "hip-hop & rap": 1,
            "house": 2,
            "maximum strength": 1,
            "rhythm & soul": 1,
            "electronic": 6,
            "dj mix": 1,
            "technology": 1,
            "deep house": 1
        }
    },
    {
        "type": "user",
        "id": 3195761,
        "permalink": "https://soundcloud.com/paul-f1-king",
        "name": "Paul F1 King",
        "likeCount": 10,
        "city": "London",
        "countryCode": "GB",
        "gender": "M",
        "genres": {
            "hard house": 1,
            "tech house": 2,
            "electronic": 2,
            "dirty funky techno dubstep..?": 1,
            "hybrid": 1,
            "sounds red": 1
        }
    },
    {
        "type": "user",
        "id": 790621,
        "permalink": "https://soundcloud.com/pabloski",
        "name": "Likemind Records",
        "likeCount": 83,
        "city": "London",
        "countryCode": null,
        "gender": "M",
        "genres": {
            "bronxdisco": 1,
            "electronic": 9,
            "techno": 5,
            "techno electro bass beats": 1,
            "downtempo": 2,
            "breaks": 1,
            "ambient": 2,
            "deep": 1,
            "new age": 1,
            "soundpiece": 1,
            "deep baseline break house": 1,
            "dream deep": 1,
            "rings around saturn": 1,
            "space n drums": 1,
            "deep house": 1
        }
    },
    {
        "type": "user",
        "id": 138916069,
        "permalink": "https://soundcloud.com/jab_es",
        "name": "Jabes",
        "likeCount": 1890,
        "city": "London",
        "countryCode": null,
        "gender": "M",
        "genres": {
            "xenonyms": 1,
            "ma3azef": 1,
            "epic mediaeval rap": 1,
            "one": 1,
            "poptimism": 1,
            "travel": 1,
            "rock": 1,
            "break": 1,
            "love": 1,
            "country": 1,
            "club": 1,
            "electronic": 4,
            "hip-hop & rap": 3,
            "functions of the now": 1,
            "remix": 1,
            "dance & edm": 2,
            "djramemes": 1,
            "jersey club": 2,
            "horrorclub": 2,
            "psychedelic carnival": 1,
            "(*(0.(0)(0)v0)*)": 1,
            "r&b & soul": 1
        }
    },
    {
        "type": "user",
        "id": 296511,
        "permalink": "https://soundcloud.com/championrecords",
        "name": "Champion Records",
        "likeCount": 155,
        "city": "London",
        "countryCode": null,
        "gender": "M",
        "genres": {
            "house": 16,
            "speed garage": 1,
            "electronic": 4,
            "tech house": 2,
            "dance / electropop": 1,
            "house breakbeat": 1,
            "electronica": 1,
            "drum & bass": 1
        }
    },
    {
        "type": "user",
        "id": 24127783,
        "permalink": "https://soundcloud.com/eurielle",
        "name": "Eurielle",
        "likeCount": 12,
        "city": "London",
        "countryCode": null,
        "gender": "M",
        "genres": {
            "soundtrack": 1,
            "thehobbit": 1,
            "r&b/soul": 1,
            "electronic": 1,
            "indie": 1,
            "alternative": 1,
            "cover": 1
        }
    },
    {
        "type": "user",
        "id": 83702,
        "permalink": "https://soundcloud.com/soulavengerz",
        "name": "Paul Gardner / Soul Avengerz",
        "likeCount": 275,
        "city": "london",
        "countryCode": "GB",
        "gender": "M",
        "genres": {
            "house": 22,
            "tech house": 3,
            "disco": 5,
            "funk": 1,
            "discohouse": 1,
            "traxsource": 2,
            "disco house": 3,
            "mix": 1,
            "essel": 1,
            "dance": 2,
            "nu disco": 1
        }
    },
    {
        "type": "user",
        "id": 149681,
        "permalink": "https://soundcloud.com/djpaulheron",
        "name": "djpaulheron",
        "likeCount": 155,
        "city": "LONDON",
        "countryCode": null,
        "gender": "M",
        "genres": {
            "calagna": 2,
            "tech house": 1,
            "house": 13,
            "1btn": 1,
            "disco": 11,
            "funk": 1,
            "dance & edm": 1,
            "deep house": 3,
            "free download": 1,
            "disco ": 1,
            "bass music": 1,
            "remix": 1,
            "funky tech house": 1,
            "nu disco": 1,
            "dancehall": 1,
            "drum & bass": 1
        }
    },
    {
        "type": "user",
        "id": 157743,
        "permalink": "https://soundcloud.com/kosteruk",
        "name": "Koster",
        "likeCount": 41,
        "city": "London",
        "countryCode": "GB",
        "gender": "M",
        "genres": {
            "house": 10,
            "electronic": 4,
            "tech house - house": 1,
            "progressive house": 1,
            "progressive": 1,
            "techno": 2,
            "dance & edm": 1,
            "tech house                              ": 1,
            "tech house": 2,
            "deep house": 1,
            "rui da silva": 1,
            "deep techno": 1
        }
    },
    {
        "type": "user",
        "id": 299425,
        "permalink": "https://soundcloud.com/johngomezldn",
        "name": "John Gomez",
        "likeCount": 93,
        "city": "London",
        "countryCode": null,
        "gender": "M",
        "genres": {
            "folk & singer-songwriter": 1,
            "interview": 2,
            "jazz & blues": 4,
            "mpb": 1,
            "boogie": 1,
            "latin": 1,
            "jazz fusion": 1,
            "ambient": 1,
            "synthpop": 1,
            "electronic": 2,
            "downtempo": 1,
            "soul": 1,
            "jazz": 1
        }
    },
    {
        "type": "user",
        "id": 1024580029,
        "permalink": "https://soundcloud.com/stone_j",
        "name": "John Stone",
        "likeCount": 499,
        "city": "London",
        "countryCode": "GB",
        "gender": "M",
        "genres": {
            "folk & singer-songwriter": 5,
            "country": 2,
            "electronic": 9,
            "alternative rock": 3,
            "blues rock": 1,
            "rock": 3,
            "hip-hop & rap": 3,
            "blues": 2,
            "folk": 1,
            "piano": 1,
            "ambient": 2,
            "classical": 1,
            "pop": 4,
            "holiday rock": 1,
            "electro core": 1,
            "trap": 2,
            "christmas rock": 1,
            "harmonize guitars 80's": 1,
            "pop rock": 1,
            "alternative": 1
        }
    },
    {
        "type": "user",
        "id": 137998,
        "permalink": "https://soundcloud.com/johnmonkman",
        "name": "John Monkman",
        "likeCount": 515,
        "city": "London",
        "countryCode": "GB",
        "gender": "M",
        "genres": {
            "progressive techno": 1,
            "melodic techno": 3,
            "alternative": 1,
            "pop electronic": 1,
            "techno": 4,
            "indie\\ disco\\ electronic": 1,
            "electronic": 7,
            "kompakt": 2,
            "deep house": 2,
            "electronic groove": 1,
            "getting deeper": 2,
            "melodic house & techno": 1,
            "cosmic": 1,
            "fatima yamaha": 1,
            "ambient": 4,
            "electronica": 1,
            "melodic house": 1,
            "yokoo": 1,
            "alternative, electronic": 1,
            "dance - house": 1
        }
    },
    {
        "type": "user",
        "id": 196511,
        "permalink": "https://soundcloud.com/senrichard",
        "name": "Richard Sen",
        "likeCount": 348,
        "city": "London",
        "countryCode": "GB",
        "gender": "M",
        "genres": {
            "techno": 2,
            "house": 6,
            "disco": 6,
            "acid house": 1,
            "void music": 5,
            "balearic/acidhouse/downtempo": 1,
            "leftfield/uk funky/electro/house/dub techno": 1,
            "electronic": 4,
            "leftfield/synth/italo/breaks/house": 1,
            "e windows": 1,
            "diy": 1,
            "deep house": 1,
            "synth/breaks/leftfield/acid/electro": 1,
            "paradia": 1,
            "jazz & blues": 1,
            "leftfield/techno/bleep/electro/detroit house": 1,
            "street": 1,
            "hard gore": 1,
            "dj set": 1,
            "dub techno/synth/techno/deep house/leftfield": 1,
            "freestyle": 1,
            "industrial house electro": 1,
            "dub/deep house/synth/acid house": 1
        }
    },
    {
        "type": "user",
        "id": 25366002,
        "permalink": "https://soundcloud.com/johnhardmanmusic-swampuk",
        "name": "John Hardman - musician, writer, producer",
        "likeCount": 8832,
        "city": "London",
        "countryCode": "GB",
        "gender": "M",
        "genres": {
            "pop": 6,
            "indie": 5,
            "alternative rock": 7,
            "folk & singer-songwriter": 11,
            "rock": 15,
            "post rock": 1,
            "electronic": 1,
            "classical": 1,
            "ambient": 1,
            "world": 1
        }
    },
    {
        "type": "user",
        "id": 6392554,
        "permalink": "https://soundcloud.com/moodena",
        "name": "MOODENA",
        "likeCount": 250,
        "city": "London",
        "countryCode": "GB",
        "gender": "M",
        "genres": {
            "disco": 18,
            "house": 6,
            "traxsource": 4,
            "electronic": 1,
            "funk | jazz | indie dance": 1,
            "deep house": 4,
            "the disco express": 1,
            "santo tomas": 1,
            "david moufang": 1,
            "nu disco, indie dance": 1,
            "skreamizm": 1
        }
    },
    {
        "type": "user",
        "id": 18416,
        "permalink": "https://soundcloud.com/nubient",
        "name": "mixmastermorris",
        "likeCount": 213,
        "city": "London",
        "countryCode": "GB",
        "gender": "M",
        "genres": {
            "soulful": 1,
            "dreambeat": 1,
            "phurther out there": 1,
            "bass": 1,
            "wax stag": 1,
            "electronic": 4,
            "music": 1,
            "young magic": 1,
            "vapourspace": 1,
            "ambient": 2,
            "kindness": 1,
            "tornado wallace": 1,
            "triphop": 1,
            "rock": 1,
            "hip hop": 1,
            "swamp81": 1,
            "<3": 1,
            "flux": 1,
            "vaporwave": 1,
            "ghostchant // capac // emerson twin": 1,
            "ambient electronic": 1,
            "og": 1,
            "r&b": 1
        }
    },
    {
        "type": "user",
        "id": 1315746693,
        "permalink": "https://soundcloud.com/sarah-myres-334137393",
        "name": "Sarah Myres",
        "likeCount": 27,
        "city": "London",
        "countryCode": "GB",
        "gender": "F",
        "genres": {
            "electronic": 2,
            "dance & edm": 4,
            "house": 5,
            "dance": 15
        }
    },
    {
        "type": "user",
        "id": 1222238635,
        "permalink": "https://soundcloud.com/sarah-monks-199928649",
        "name": "Sarah Monks",
        "likeCount": 18,
        "city": "London",
        "countryCode": "GB",
        "gender": "F",
        "genres": {
            "electronic": 3,
            "dance & edm": 5,
            "house": 6,
            "techno": 3
        }
    },
    {
        "type": "user",
        "id": 15333448,
        "permalink": "https://soundcloud.com/sarah-de-warren",
        "name": "Sarah de Warren",
        "likeCount": 332,
        "city": "London",
        "countryCode": "GB",
        "gender": "F",
        "genres": {
            "dance & edm": 12,
            "techno": 1,
            "entertainment": 1,
            "house": 1,
            "dance": 12,
            "electronic": 7,
            "deep house": 1,
            "electro house": 1,
            "realprog": 1,
            "trance": 1,
            "pop": 1
        }
    },
    {
        "type": "user",
        "id": 4735397,
        "permalink": "https://soundcloud.com/sarahtonindj",
        "name": "Sarahtonin",
        "likeCount": 620,
        "city": "London",
        "countryCode": "GB",
        "gender": "F",
        "genres": {
            "deep house": 3,
            "electronic": 4,
            "house": 7,
            "love": 1,
            "anthem edit ": 1,
            "world": 1,
            "rinse fm": 1,
            "danny": 1,
            "arabic disco": 1,
            "7th heaven": 1,
            "ambient/jazz/downtempo": 1,
            "disco": 2,
            "present perfect festival": 1,
            "r&b & soul": 1,
            "hunch music": 1,
            "pop": 1,
            "ukg": 1,
            "love hypnosis": 1
        }
    },
    {
        "type": "user",
        "id": 8742536,
        "permalink": "https://soundcloud.com/shifty-doll-1",
        "name": "SHIFTY LDN",
        "likeCount": 54,
        "city": "London",
        "countryCode": "GB",
        "gender": "F",
        "genres": {
            "deep house": 6,
            "house": 6,
            "minimal": 1,
            "reggae": 1,
            "tech house": 1,
            "g house": 1,
            "meoko": 1,
            "jnr windross ": 1,
            "salah": 1,
            "mr g ": 1,
            "cozzyd": 1,
            "lee b3 edwards": 1,
            "techno": 2,
            "odd music": 1,
            "tech-house": 1
        }
    },
    {
        "type": "user",
        "id": 8718763,
        "permalink": "https://soundcloud.com/sarahrnb24",
        "name": "Sarahrnb30",
        "likeCount": 3,
        "city": "london",
        "countryCode": "GB",
        "gender": "F",
        "genres": {
            "hip-hop & rap": 2,
            "hiphop en rap": 1
        }
    },
    {
        "type": "user",
        "id": 59868819,
        "permalink": "https://soundcloud.com/sarahshamash3",
        "name": "Sarah Shamash 3",
        "likeCount": 282,
        "city": "London",
        "countryCode": null,
        "gender": "F",
        "genres": {
            "electronic": 2,
            "triphop": 1,
            "piano": 1,
            "hip-hop & rap": 2,
            "music": 1,
            "instrumental": 1,
            "indie": 2,
            "soulful": 1,
            "ambient": 1,
            "electro": 2,
            "learning": 1,
            "retro": 1,
            "alternative rock": 3,
            "folk & singer-songwriter": 1,
            "jazz": 2,
            "funky": 1,
            "bill withers": 1,
            "drum & bass": 4,
            "dnb": 2,
            "psy-trance": 1,
            "dubstep": 2,
            "trap": 1,
            "edm": 1,
            "music #india style #dubstep": 1,
            "french house": 1,
            "zion i  g jones": 1,
            "bass house": 1
        }
    },
    {
        "type": "user",
        "id": 10198536,
        "permalink": "https://soundcloud.com/lexluca",
        "name": "Lex Luca",
        "likeCount": 147,
        "city": "London",
        "countryCode": null,
        "gender": "F",
        "genres": {
            "deep tech": 2,
            "lex luca": 1,
            "house": 18,
            "organic house": 1,
            "ny house": 1,
            "deep house": 1,
            "tech house": 5,
            "dh077": 1,
            "electronic": 3
        }
    },
    {
        "type": "user",
        "id": 166710031,
        "permalink": "https://soundcloud.com/sarahteibomusic",
        "name": "Sarah Teibo Music",
        "likeCount": 7,
        "city": "London",
        "countryCode": null,
        "gender": "F",
        "genres": {
            "leap": 1,
            "electronic-pop": 1,
            "gospel": 1,
            "world": 1,
            "sarah teibo": 1,
            "cover": 1,
            "inspirational": 1
        }
    },
    {
        "type": "user",
        "id": 12797254,
        "permalink": "https://soundcloud.com/ejbradbry",
        "name": "ejbradbry",
        "likeCount": 24,
        "city": "London",
        "countryCode": "GB",
        "gender": "F",
        "genres": {
            "electronic": 2,
            "techno": 9,
            "playa tech": 1,
            "wuitw": 1,
            "tech house": 1,
            "warehouse mode": 1,
            "innervisions": 1,
            "guy j": 1,
            "acid": 1
        }
    },
    {
        "type": "user",
        "id": 19248691,
        "permalink": "https://soundcloud.com/missstakes-1",
        "name": "Missstakes",
        "likeCount": 3,
        "city": "London",
        "countryCode": "GB",
        "gender": "F",
        "genres": {}
    },
    {
        "type": "user",
        "id": 108930959,
        "permalink": "https://soundcloud.com/dylan-allcock",
        "name": "Dylan Allcock",
        "likeCount": 19,
        "city": "London",
        "countryCode": "GB",
        "gender": "F",
        "genres": {
            "musical theatre": 2,
            "electronic": 1,
            "piano": 4,
            "classical": 1,
            "sundogs": 1,
            "mahler8": 1,
            "alternrock": 1,
            "rock": 2,
            "keith": 1,
            "soundtrack": 1,
            "keith kenniff": 1
        }
    },
    {
        "type": "user",
        "id": 26673809,
        "permalink": "https://soundcloud.com/lauraklo",
        "name": "Maybe Laura",
        "likeCount": 880,
        "city": "London",
        "countryCode": null,
        "gender": "F",
        "genres": {
            "ambient": 17,
            "psychedelic ambient": 1,
            "sundays": 1,
            "experimental": 1,
            "folk rock": 1,
            "electronic": 6,
            "drum & bass": 1,
            "intrinsic": 6,
            "downtempo": 1,
            "electronica": 1,
            "deep house": 1,
            "modem festival": 2,
            "r&b & soul": 1,
            "pop": 1
        }
    },
    {
        "type": "user",
        "id": 3786484,
        "permalink": "https://soundcloud.com/julianlennon",
        "name": "julianlennon",
        "likeCount": 1,
        "city": "London",
        "countryCode": "GB",
        "gender": "F",
        "genres": {
            "rock": 1
        }
    },
    {
        "type": "user",
        "id": 189878032,
        "permalink": "https://soundcloud.com/laura-garnier-130702326",
        "name": "Laura Garnier",
        "likeCount": 3,
        "city": "London",
        "countryCode": "GB",
        "gender": "F",
        "genres": {
            "dubs": 1,
            "rock": 1,
            "remix": 1
        }
    },
    {
        "type": "user",
        "id": 1520315,
        "permalink": "https://soundcloud.com/laurastevenspop",
        "name": "Laura Stevens (Pop/Commercial Writing)",
        "likeCount": 14,
        "city": "London",
        "countryCode": null,
        "gender": "F",
        "genres": {
            "brit pop": 1,
            "indie pop": 1
        }
    }
]